{
    "twBaseStats": {
        "!PustotA10M": {
            "name": "Salt",
            "trip": "!PustotA10M",
            "energy": 774,
            "shkvarki": {},
            "title": {
                "from": "!/kyOuko.4A",
                "cost": 10,
                "title": "Солевой"
            },
            "prev": 774
        },
        "!YnrKuf9gkA": {
            "name": "Rika",
            "trip": "!YnrKuf9gkA",
            "energy": 702,
            "shkvarki": {},
            "title": null,
            "prev": 702
        },
        "!mironaxxOY": {
            "name": "Oxxxy",
            "trip": "!mironaxxOY",
            "energy": 569,
            "shkvarki": {},
            "title": {
                "from": "!/kyOuko.4A",
                "cost": 40,
                "title": "Евреечка"
            },
            "prev": 569
        },
        "!B4inUX7.e.": {
            "name": "Horo",
            "trip": "!B4inUX7.e.",
            "energy": 229,
            "shkvarki": {},
            "title": null,
            "prev": 229
        },
        "!RIEExrBWWo": {
            "name": "Etna",
            "trip": "!RIEExrBWWo",
            "energy": 834,
            "shkvarki": {},
            "title": null,
            "prev": 834
        },
        "!Cute": {
            "name": "Сумеречная Кискорка",
            "trip": "!Cute",
            "energy": 1233,
            "shkvarki": {},
            "title": null,
            "prev": 1233
        },
        "!!Hsg3qWycuc": {
            "name": "Уцуха",
            "trip": "!!Hsg3qWycuc",
            "energy": 293,
            "shkvarki": {
                "!μ μ μ μ": true
            },
            "title": null,
            "prev": 293
        },
        "!ShinkuLpCY": {
            "name": "Shinku_fag",
            "trip": "!ShinkuLpCY",
            "energy": 268,
            "shkvarki": {},
            "title": null,
            "prev": 268
        },
        "!John Dowson": {
            "name": "",
            "trip": "!John Dowson",
            "energy": 100,
            "shkvarki": {},
            "title": null,
            "prev": 100
        },
        "!UtkaQqQJQM": {
            "name": "Утейка",
            "trip": "!UtkaQqQJQM",
            "energy": 996,
            "shkvarki": {},
            "title": null,
            "prev": 996
        },
        "!K0xIzQQYRs": {
            "name": "eva ",
            "trip": "!K0xIzQQYRs",
            "energy": 650,
            "shkvarki": {},
            "title": {
                "from": "!/kyOuko.4A",
                "cost": 10,
                "title": "Больше не котейка"
            },
            "prev": 650
        },
        "!HaGudFIQ3Y": {
            "name": "Suigintou",
            "trip": "!HaGudFIQ3Y",
            "energy": 89,
            "shkvarki": {},
            "title": null,
            "prev": 89
        },
        "!e93w6BLas2": {
            "name": "Nonon2",
            "trip": "!e93w6BLas2",
            "energy": 274,
            "shkvarki": {},
            "title": null,
            "prev": 274
        },
        "!KAPITANm0g": {
            "name": "Шепард",
            "trip": "!KAPITANm0g",
            "energy": 334,
            "shkvarki": {},
            "title": null,
            "prev": 334
        },
        "!OWKiocPMbI": {
            "name": "Yudachi",
            "trip": "!OWKiocPMbI",
            "energy": 25,
            "shkvarki": {},
            "title": null,
            "prev": 25
        },
        "!axtZ4SSxZ2": {
            "name": "Zonesama",
            "trip": "!axtZ4SSxZ2",
            "energy": 597,
            "shkvarki": {},
            "title": null,
            "prev": 597
        },
        "!/kyOuko.4A": {
            "name": "Kyouko Sakura",
            "trip": "!/kyOuko.4A",
            "energy": 520,
            "shkvarki": {},
            "title": null,
            "prev": 520
        },
        "!LUPerKALRk": {
            "name": "Хорушка",
            "trip": "!LUPerKALRk",
            "energy": 7,
            "shkvarki": {},
            "title": null,
            "prev": 7
        },
        "!gWmE72hUM.": {
            "name": "Hina",
            "trip": "!gWmE72hUM.",
            "energy": 95,
            "shkvarki": {},
            "title": null,
            "prev": 95
        },
        "!qk7yf3WNdQ": {
            "name": "Bernbern",
            "trip": "!qk7yf3WNdQ",
            "energy": 79,
            "shkvarki": {},
            "title": null,
            "prev": 79
        },
        "!vEJ5jocEzo": {
            "name": "Пепе",
            "trip": "!vEJ5jocEzo",
            "energy": 22,
            "shkvarki": {},
            "title": null,
            "prev": 22
        },
        "!Mondbeschie": {
            "name": "",
            "trip": "!Mondbeschie",
            "energy": 48,
            "shkvarki": {},
            "title": null,
            "prev": 48
        },
        "!rose//scQs": {
            "name": "",
            "trip": "!rose//scQs",
            "energy": 172,
            "shkvarki": {},
            "title": null,
            "prev": 172
        },
        "!casterQPFA": {
            "name": "Medea",
            "trip": "!casterQPFA",
            "energy": 1,
            "shkvarki": {},
            "title": null,
            "prev": 1
        },
        "newfag": {
            "name": "",
            "trip": "newfag",
            "energy": 2,
            "shkvarki": {},
            "title": null,
            "prev": 2
        },
        "!nyasha.1Kk": {
            "name": "Ами ",
            "trip": "!nyasha.1Kk",
            "energy": 444,
            "shkvarki": {},
            "title": null,
            "prev": 444
        },
        "!!R06JSP5uFk": {
            "name": "Renge",
            "trip": "!!R06JSP5uFk",
            "energy": 371,
            "shkvarki": {},
            "title": {
                "from": "!/kyOuko.4A",
                "cost": 10,
                "title": "Порнодевочка"
            },
            "prev": 371
        },
        "!!4pBF6TDQac": {
            "name": "Немец",
            "trip": "!!4pBF6TDQac",
            "energy": 244,
            "shkvarki": {},
            "title": null,
            "prev": 244
        },
        "!μ μ μ μ": {
            "name": "Sea serpent",
            "trip": "!μ μ μ μ",
            "energy": 126,
            "shkvarki": {},
            "title": null,
            "prev": 126
        },
        "!YlTclYE5cI": {
            "name": "",
            "trip": "!YlTclYE5cI",
            "energy": 2,
            "shkvarki": {},
            "title": null,
            "prev": 2
        },
        "!w8p4boyE0M": {
            "name": "",
            "trip": "!w8p4boyE0M",
            "energy": 1,
            "shkvarki": {},
            "title": null,
            "prev": 1
        },
        "!78Z.QqvS8E": {
            "name": "",
            "trip": "!78Z.QqvS8E",
            "energy": 6,
            "shkvarki": {},
            "title": null,
            "prev": 6
        },
        "!cPqgsjl4yM": {
            "name": "",
            "trip": "!cPqgsjl4yM",
            "energy": 1,
            "shkvarki": {},
            "title": null,
            "prev": 1
        },
        "!E9PwLBjS4.": {
            "name": "",
            "trip": "!E9PwLBjS4.",
            "energy": 2,
            "shkvarki": {},
            "title": null,
            "prev": 2
        },
        "!Tq/zRlgZJs": {
            "name": "",
            "trip": "!Tq/zRlgZJs",
            "energy": 1,
            "shkvarki": {},
            "title": null,
            "prev": 1
        },
        "!eqO9IwwU.Q": {
            "name": "Lan",
            "trip": "!eqO9IwwU.Q",
            "energy": 141,
            "shkvarki": {},
            "title": null,
            "prev": 141
        },
        "!5renzyjjOk": {
            "name": "5renzy",
            "trip": "!5renzyjjOk",
            "energy": 195,
            "shkvarki": {},
            "title": null,
            "prev": 195
        },
        "!.CzKQna1OU": {
            "name": "test",
            "trip": "!.CzKQna1OU",
            "energy": 1,
            "shkvarki": {},
            "title": null,
            "prev": 1
        },
        "!FQYKueyWq2": {
            "name": "lampa",
            "trip": "!FQYKueyWq2",
            "energy": 31,
            "shkvarki": {},
            "title": null,
            "prev": 31
        },
        "!!ws7mYS1ubY": {
            "name": "Канария-тульповод",
            "trip": "!!ws7mYS1ubY",
            "energy": 2,
            "shkvarki": {},
            "title": null,
            "prev": 2
        },
        "!!gbh2pgG4MQ": {
            "name": "Sou",
            "trip": "!!gbh2pgG4MQ",
            "energy": 152,
            "shkvarki": {},
            "title": null,
            "prev": 152
        },
        "!1iPGyk7RXM": {
            "name": "Nonon3",
            "trip": "!1iPGyk7RXM",
            "energy": 3,
            "shkvarki": {},
            "title": null,
            "prev": 3
        },
        "!DJsonaNFyg": {
            "name": "Sona",
            "trip": "!DJsonaNFyg",
            "energy": 2,
            "shkvarki": {},
            "title": null,
            "prev": 2
        },
        "!TrIPcoDE6.": {
            "name": "Jesse",
            "trip": "!TrIPcoDE6.",
            "energy": 42,
            "shkvarki": {},
            "title": null,
            "prev": 42
        },
        "!SHOGUNq31E": {
            "name": "Wo-Class",
            "trip": "!SHOGUNq31E",
            "energy": 12,
            "shkvarki": {},
            "title": null,
            "prev": 12
        },
        "!0NESaifer.": {
            "name": "Saifer",
            "trip": "!0NESaifer.",
            "energy": 29,
            "shkvarki": {},
            "title": null,
            "prev": 29
        },
        "!!IMF0IzheJ2": {
            "name": "Madoka!",
            "trip": "!!IMF0IzheJ2",
            "energy": 53,
            "shkvarki": {},
            "title": null,
            "prev": 53
        },
        "!wsZeuflIao": {
            "name": "",
            "trip": "!wsZeuflIao",
            "energy": 233,
            "shkvarki": {},
            "title": null,
            "prev": 233
        },
        "!ec6J/SEAhE": {
            "name": "",
            "trip": "!ec6J/SEAhE",
            "energy": 2,
            "shkvarki": {},
            "title": null,
            "prev": 2
        },
        "!92Ypa3esbo": {
            "name": "Беззубик",
            "trip": "!92Ypa3esbo",
            "energy": 6,
            "shkvarki": {},
            "title": null,
            "prev": 6
        },
        "!zNDIscOrd2": {
            "name": " Бог-Император Антарктиды",
            "trip": "!zNDIscOrd2",
            "energy": 7,
            "shkvarki": {},
            "title": null,
            "prev": 7
        },
        "!GzJCRqWwU6": {
            "name": "Такеши",
            "trip": "!GzJCRqWwU6",
            "energy": 17,
            "shkvarki": {},
            "title": null,
            "prev": 17
        },
        "!Qwpd7/AtbY": {
            "name": "Fubuki-chan",
            "trip": "!Qwpd7/AtbY",
            "energy": 512,
            "shkvarki": {},
            "title": null,
            "prev": 512
        },
        "!GgGinToUxM": {
            "name": "Suigintou",
            "trip": "!GgGinToUxM",
            "energy": 1,
            "shkvarki": {},
            "title": null,
            "prev": 1
        },
        "!3GINTOujG.": {
            "name": "Suigintou",
            "trip": "!3GINTOujG.",
            "energy": 244,
            "shkvarki": {},
            "title": null,
            "prev": 244
        },
        "!!SnJWLroumc": {
            "name": "Сусека ",
            "trip": "!!SnJWLroumc",
            "energy": 14,
            "shkvarki": {},
            "title": null,
            "prev": 14
        }
    },
    "twBaseThread": "2207468"
}
